adkgc/__init__.py
adkgc-0.0.1.dist-info/METADATA
adkgc-0.0.1.dist-info/WHEEL
adkgc-0.0.1.dist-info/top_level.txt
adkgc-0.0.1.dist-info/RECORD
