Metadata-Version: 2.4
Name: adkgc
Version: 0.0.1
Summary: Wrapper To Create Google Chat Bot For Agents Implemented With ADK
Author: Viacheslav Kovalevskyi
Author-email: viacheslav@kovalevskyi.com
License: MIT
Requires-Dist: google-cloud-pubsub==2.29.*
Requires-Dist: google-api-python-client==2.166.*
Requires-Dist: google-auth==2.38.*
Requires-Dist: google-auth-httplib2==0.2.*
Requires-Dist: python-dotenv==1.1
Requires-Dist: google-adk==0.1.*
Requires-Dist: Flask==3.1.*
Dynamic: author
Dynamic: author-email
Dynamic: description
Dynamic: description-content-type
Dynamic: license
Dynamic: requires-dist
Dynamic: summary
